
{"signal":[["Inputs",{"name":"clk","wave":"lhlhlhlhlhlhlhlhlhlhlhlhlhlhlhlhlhlhl"},{"name":"slowena","wave":"1...................................."},{"name":"reset","wave":"1..0......1..0......................."}],{"name":""},["Yours",{"name":"q","wave":"=....=.=.=.=...=.=.=.=.=.=.=.=.=.=.=.","data":["0","1","2","3","0","1","2","3","4","5","6","7","8","9","0","1"]}],{"name":""},["Ref",{"name":"q","wave":"x=...=.=.=.=...=.=.=.=.=.=.=.=.=.=.=.","data":["0","1","2","3","0","1","2","3","4","5","6","7","8","9","0","1"]}],{"name":""},{"name":"Mismatch:","wave":"l...................................."}],"foot":{"tick":["",["tspan",{"font-size":9},"10"],"",["tspan",{"font-size":9},"20"],"",["tspan",{"font-size":9},"30"],"",["tspan",{"font-size":9},"40"],"",["tspan",{"font-size":9},"50"],"",["tspan",{"font-size":9},"60"],"",["tspan",{"font-size":9},"70"],"",["tspan",{"font-size":9},"80"],"",["tspan",{"font-size":9},"90"],"",["tspan",{"font-size":9},"100"],"",["tspan",{"font-size":9},"110"],"",["tspan",{"font-size":9},"120"],"",["tspan",{"font-size":9},"130"],"",["tspan",{"font-size":9},"140"],"",["tspan",{"font-size":9},"150"],"",["tspan",{"font-size":9},"160"],"",["tspan",{"font-size":9},"170"],"",["tspan",{"font-size":9},"180"],""]},"config":{"hscale":1}}
